blobid/__init__.py
blobid/_domain.py
blobid/_numba_support.py
blobid/solver.py
blobid/labeling/__init__.py
blobid/labeling/ccl.py
blobid/labeling/database.py
blobid/labeling/labeling.py
blobid/plic/__init__.py
blobid/plic/analytic_relations.py
blobid/plic/central_difference.py
blobid/plic/nivira.py
blobid/plic/plic.py
blobid-0.6.1.dist-info/licenses/LICENSE
blobid-0.6.1.dist-info/METADATA
blobid-0.6.1.dist-info/WHEEL
blobid-0.6.1.dist-info/top_level.txt
blobid-0.6.1.dist-info/RECORD
