Metadata-Version: 2.4
Name: blobid
Version: 0.6.1
Summary: Identify bubbles/droplets based on volume of fluid (VOF) simulation data
Author: Declan B. Gaylo
License-Expression: MIT
Project-URL: Homepage, https://github.com/dgaylo/blobid-python
Project-URL: Bug Tracker, https://github.com/dgaylo/blobid-python/issues
Project-URL: Documentation, https://dgaylo.github.io/blobid-python
Classifier: Programming Language :: Python :: 3
Classifier: Operating System :: OS Independent
Requires-Python: >=3.10
License-File: LICENSE
Requires-Dist: numpy>=1
Provides-Extra: numba
Requires-Dist: numba; extra == "numba"
Dynamic: license-file
